humac_tools/__init__.py
humac_tools/tools.py
humac_tools_library-0.1.1.dist-info/licenses/LICENSE
humac_tools_library-0.1.1.dist-info/METADATA
humac_tools_library-0.1.1.dist-info/WHEEL
humac_tools_library-0.1.1.dist-info/top_level.txt
humac_tools_library-0.1.1.dist-info/RECORD
