Metadata-Version: 2.4
Name: humac_tools_library
Version: 0.1.1
Summary: A simple Python library with correlation, seasonality ,optimzedGecode,graphExplainer,detectAnomalies  plus advanced data analysis tools.
Home-page: https://github.com/humacpspl/humac_tools_library.git
Author: somanath
Author-email: shindesomanath111@gamil.com
Classifier: Programming Language :: Python :: 3
Classifier: License :: OSI Approved :: MIT License
Classifier: Operating System :: OS Independent
Requires-Python: >=3.6
License-File: LICENSE
Requires-Dist: sqlalchemy==2.0.37
Requires-Dist: statsmodels==0.14.4
Requires-Dist: scipy==1.15.3
Requires-Dist: pytest==8.3.5
Requires-Dist: python-dotenv==1.0.1
Requires-Dist: pyjwt==2.10.1
Requires-Dist: matplotlib==3.10.3
Requires-Dist: rapidfuzz==3.13.0
Requires-Dist: scikit-learn==1.6.1
Requires-Dist: pandas
Requires-Dist: numpy
Dynamic: author
Dynamic: author-email
Dynamic: classifier
Dynamic: description
Dynamic: description-content-type
Dynamic: home-page
Dynamic: license-file
Dynamic: requires-dist
Dynamic: requires-python
Dynamic: summary
